hdtv/__init__.py
hdtv/_version.py
hdtv/app.py
hdtv/cal.py
hdtv/cmdline.py
hdtv/color.py
hdtv/cut.py
hdtv/drawable.py
hdtv/dummy.py
hdtv/fit.py
hdtv/fitpanel.py
hdtv/fitter.py
hdtv/fitxml.py
hdtv/histogram.py
hdtv/hsluv.py
hdtv/integral.py
hdtv/marker.py
hdtv/matrix.py
hdtv/options.py
hdtv/rfile_utils.py
hdtv/session.py
hdtv/specreader.py
hdtv/spectrum.py
hdtv/tabformat.py
hdtv/ui.py
hdtv/util.py
hdtv/weakref_proxy.py
hdtv/window.py
hdtv/backgroundmodels/__init__.py
hdtv/backgroundmodels/background.py
hdtv/backgroundmodels/exponential.py
hdtv/backgroundmodels/interpolation.py
hdtv/backgroundmodels/polynomial.py
hdtv/database/DDEPLibraries.py
hdtv/database/IAEALibraries.py
hdtv/database/PGAALibraries.py
hdtv/database/__init__.py
hdtv/database/common.py
hdtv/efficiency/__init__.py
hdtv/efficiency/efficiency.py
hdtv/efficiency/exp.py
hdtv/efficiency/polyeff.py
hdtv/efficiency/pow.py
hdtv/efficiency/wiedenhoever.py
hdtv/efficiency/wunder.py
hdtv/peakmodels/__init__.py
hdtv/peakmodels/eePeak.py
hdtv/peakmodels/peak.py
hdtv/peakmodels/theuerkaufPeak.py
hdtv/plugins/EnergyCalibration.py
hdtv/plugins/__init__.py
hdtv/plugins/calInterface.py
hdtv/plugins/config.py
hdtv/plugins/dblookup.py
hdtv/plugins/fitInterface.py
hdtv/plugins/fitlist.py
hdtv/plugins/fitmap.py
hdtv/plugins/fittex.py
hdtv/plugins/ls.py
hdtv/plugins/matInterface.py
hdtv/plugins/peakfinder.py
hdtv/plugins/printing.py
hdtv/plugins/rootInterface.py
hdtv/plugins/run.py
hdtv/plugins/specInterface.py
hdtv/plugins/textInterface.py
hdtv/rootext/__init__.py
hdtv/rootext/calibration.py
hdtv/rootext/display.py
hdtv/rootext/dlmgr.py
hdtv/rootext/fit.py
hdtv/rootext/mfile.py
hdtv/rootext/calibration/CMakeLists.txt
hdtv/rootext/calibration/Calibration.cc
hdtv/rootext/calibration/Calibration.hh
hdtv/rootext/calibration/LinkDef.h
hdtv/rootext/display/CMakeLists.txt
hdtv/rootext/display/DisplayBlock.cc
hdtv/rootext/display/DisplayBlock.hh
hdtv/rootext/display/DisplayCut.cc
hdtv/rootext/display/DisplayCut.hh
hdtv-24.10.dist-info/METADATA
hdtv-24.10.dist-info/WHEEL
hdtv-24.10.dist-info/entry_points.txt
hdtv-24.10.dist-info/top_level.txt
hdtv-24.10.dist-info/RECORD
