Metadata-Version: 2.1
Name: hdtv
Version: 24.10
Summary: HDTV - Nuclear Spectrum Analysis Tool
Home-page: https://github.com/janmayer/hdtv
Maintainer: Jan Mayer
Maintainer-email: jan.mayer@ikp.uni-koeln.de
License: GPL
Keywords: analysis data-analysis gamma-spectroscopy nuclear-physics nuclear-spectrum-analysis physics python root root-cern spectroscopy
Classifier: Development Status :: 5 - Production/Stable
Classifier: Environment :: Console
Classifier: Environment :: X11 Applications
Classifier: Intended Audience :: Information Technology
Classifier: Intended Audience :: Science/Research
Classifier: License :: OSI Approved :: GNU General Public License v2 or later (GPLv2+)
Classifier: Natural Language :: English
Classifier: Operating System :: MacOS
Classifier: Operating System :: POSIX
Classifier: Operating System :: POSIX :: Linux
Classifier: Programming Language :: C
Classifier: Programming Language :: C++
Classifier: Programming Language :: Python
Classifier: Programming Language :: Python :: 3
Classifier: Programming Language :: Python :: 3.8
Classifier: Programming Language :: Python :: 3.9
Classifier: Programming Language :: Python :: 3.10
Classifier: Programming Language :: Python :: 3.11
Classifier: Topic :: Scientific/Engineering
Classifier: Topic :: Scientific/Engineering :: Information Analysis
Classifier: Topic :: Scientific/Engineering :: Physics
Classifier: Topic :: Scientific/Engineering :: Visualization
Requires-Dist: scipy
Requires-Dist: matplotlib
Requires-Dist: numpy
Requires-Dist: ipython
Requires-Dist: prompt-toolkit>=3.0.14
Requires-Dist: traitlets
Requires-Dist: uncertainties
Provides-Extra: dev
Requires-Dist: docutils; extra == "dev"
Provides-Extra: test
Requires-Dist: pytest; extra == "test"
Requires-Dist: pytest-cov; extra == "test"
